{
  "resourceType": "Patient",
  "id": "f8f6db646bc75f1f1788bc50212156e3b28742721d4fc08787355f2f4af81fa6",
  "meta": {
    "security": [
      {
        "system": "http://terminology.hl7.org/CodeSystem/v3-ObservationValue",
        "code": "REDACTED",
        "display": "part of the resource is removed"
      },
      {
        "system": "http://terminology.hl7.org/CodeSystem/v3-ObservationValue",
        "code": "CRYTOHASH",
        "display": "exact value is transformed with a hash function"
      }
    ]
  },
  "identifier": [
    {
      "use": "usual",
      "type": {
        "coding": [
          {
            "system": "http://hl7.org/fhir/v2/0203"
          }
        ]
      },
      "system": "urn:oid:0.1.2.3.4.5.6.7"
    }
  ],
  "active": true,
  "name": [
    {
      "use": "official"
    }
  ],
  "gender": "other",
  "photo": [
    {
      "contentType": "image/gif"
    }
  ],
  "managingOrganization": {
    "reference": "Organization/9400891ae111f2b41e57a96d587e6872f11e9380a005ff16ea9e1b8b0e234922"
  },
  "link": [
    {
      "other": {
        "reference": "Patient/54e7c6864954855ec5cbecd49f10bde45a679f7223f2920d34a59ef6b16f44d7"
      },
      "type": "seealso"
    }
  ]
}